FlexDB/__init__.py
FlexDB-0.0.1.dist-info/LICENSE
FlexDB-0.0.1.dist-info/METADATA
FlexDB-0.0.1.dist-info/WHEEL
FlexDB-0.0.1.dist-info/top_level.txt
FlexDB-0.0.1.dist-info/RECORD
