Metadata-Version: 2.1
Name: FlexDB
Version: 0.0.1
Summary: FlexDB - A simple, fast, and lightweight database for storing and retrieving data.
Home-page: https://github.com/Almas-Ali/FlexDB
Author: Md. Almas Ali
Author-email: almaspr3@gmail.com
License: GNU General Public License v3 (GPLv3)
Platform: UNKNOWN
Classifier: Development Status :: 2 - Pre-Alpha
Classifier: Operating System :: OS Independent
Classifier: Intended Audience :: Developers
Classifier: License :: OSI Approved :: GNU General Public License v3 (GPLv3)
Classifier: Programming Language :: Python :: 3
Classifier: Topic :: Software Development :: Libraries :: Python Modules
Classifier: Topic :: Database
Classifier: Natural Language :: English
Classifier: Environment :: Console
Classifier: Environment :: Web Environment
License-File: LICENSE
